pyckles/__init__.py
pyckles/index.dat
pyckles/spectral_library.py
pyckles/tests/__init__.py
pyckles/tests/test_spectral_library.py
pyckles/tests/test_utils.py
pyckles/utils.py
pyckles-0.6.0.dist-info/LICENSE
pyckles-0.6.0.dist-info/METADATA
pyckles-0.6.0.dist-info/WHEEL
pyckles-0.6.0.dist-info/RECORD
