Metadata-Version: 2.3
Name: Pyckles
Version: 0.6.0
Summary: Simple interface to the Pickles 1998 stellar spectra catalogue.
License: GPL-3.0-or-later
Keywords: astronomy
Author: Kieran Leschinski
Author-email: kieran.leschinski@univie.ac.at
Maintainer: Kieran Leschinski
Maintainer-email: kieran.leschinski@univie.ac.at
Requires-Python: >=3.10,<3.15
Classifier: Intended Audience :: Science/Research
Classifier: License :: OSI Approved :: GNU General Public License v3 or later (GPLv3+)
Classifier: Operating System :: OS Independent
Classifier: Programming Language :: Python :: 3
Classifier: Programming Language :: Python :: 3.10
Classifier: Programming Language :: Python :: 3.11
Classifier: Programming Language :: Python :: 3.12
Classifier: Programming Language :: Python :: 3.13
Classifier: Topic :: Scientific/Engineering :: Astronomy
Provides-Extra: syn
Requires-Dist: astropy (>=6.1.7,<8.0.0)
Requires-Dist: pooch (>=1.8.2,<2.0.0)
Requires-Dist: scipy (>=1.15.3,<1.16.0) ; python_version == "3.10"
Requires-Dist: scipy (>=1.17.0,<1.18.0) ; python_version >= "3.11"
Requires-Dist: synphot (>=1.5.0,<2.0.0) ; extra == "syn"
Project-URL: Bug Tracker, https://github.com/AstarVienna/Pyckles/issues
Project-URL: Changelog, https://github.com/AstarVienna/Pyckles/blob/main/CHANGELOG.md
Project-URL: Documentation, https://pyckles.readthedocs.io/
Project-URL: Repository, https://github.com/AstarVienna/Pyckles/
